Workbook

Sheet Sample - Superstore
A1: Row ID | B1: Order ID | C1: Order Date | D1: Ship Date | E1: Ship Mode | F1: Customer ID | G1: Customer Name | H1: Segment | I1: Country | J1: City | K1: State | L1: Postal Code | M1: Region | N1: Product ID | O1: Category | P1: Sub-Category | Q1: Product Name | R1: Sales | S1: Quantity | T1: Discount | U1: Profit | V1: Order Year | W1: Order Month | X1: Year-Month | Y1: Profit Margin | Z1: Shipping Days | AA1: Profit per Unit | AB1: Sales per Unit | AC1: Discount Amount | AD1: Net Sales
A2: 1 | B2: CA-2016-152156 | C2: 42682 | D2: 42685 | E2: Second Class | F2: CG-12520 | G2: Claire Gute | H2: Consumer | I2: United States | J2: Henderson | K2: Kentucky | L2: 42420 | M2: South | N2: FUR-BO-10001798 | O2: Furniture | P2: Bookcases | Q2: Bush Somerset Collection Bookcase | R2: 261.96 | S2: 2 | T2: 0 | U2: 41.9136 | V2: =YEAR(C2) -> 2016 | W2: =TEXT(C2,"mmm") -> Nov | X2: =Sample___Superstore[[#This Row],[Order Year]]&"-"&Sample___Superstore[[#This Row],[Order Month]] -> 2016-Nov | Y2: =Sample___Superstore6[[#This Row],[Profit]]/Sample___Superstore6[[#This Row],[Sales]] -> 0.16 | Z2: =D2-C2 -> 3 | AA2: =U2/S2 -> 20.9568 | AB2: =R2/S2 -> 130.98 | AC2: =R2*T2 -> 0 | AD2: =R2-(R2*T2) -> 261.96
A3: 2 | B3: CA-2016-152156 | C3: 42682 | D3: 42685 | E3: Second Class | F3: CG-12520 | G3: Claire Gute | H3: Consumer | I3: United States | J3: Henderson | K3: Kentucky | L3: 42420 | M3: South | N3: FUR-CH-10000454 | O3: Furniture | P3: Chairs | Q3: Hon Deluxe Fabric Upholstered Stacking Chairs, Rounded Back | R3: 731.94 | S3: 3 | T3: 0 | U3: 219.582 | V3: =YEAR(C3) -> 2016 | W3: =TEXT(C3,"mmm") -> Nov | X3: =Sample___Superstore[[#This Row],[Order Year]]&"-"&Sample___Superstore[[#This Row],[Order Month]] -> 2016-Nov | Y3: =Sample___Superstore6[[#This Row],[Profit]]/Sample___Superstore6[[#This Row],[Sales]] -> 0.3 | Z3: =D3-C3 -> 3 | AA3: =U3/S3 -> 73.194 | AB3: =R3/S3 -> 243.98 | AC3: =R3*T3 -> 0 | AD3: =R3-(R3*T3) -> 731.94
A4: 3 | B4: CA-2016-138688 | C4: 42533 | D4: 42537 | E4: Second Class | F4: DV-13045 | G4: Darrin Van Huff | H4: Corporate | I4: United States | J4: Los Angeles | K4: California | L4: 90036 | M4: West | N4: OFF-LA-10000240 | O4: Office Supplies | P4: Labels | Q4: Self-Adhesive Address Labels for Typewriters by Universal | R4: 14.62 | S4: 2 | T4: 0 | U4: 6.8714 | V4: =YEAR(C4) -> 2016 | W4: =TEXT(C4,"mmm") -> Jun | X4: =Sample___Superstore[[#This Row],[Order Year]]&"-"&Sample___Superstore[[#This Row],[Order Month]] -> 2016-Jun | Y4: =Sample___Superstore6[[#This Row],[Profit]]/Sample___Superstore6[[#This Row],[Sales]] -> 0.47 | Z4: =D4-C4 -> 4 | AA4: =U4/S4 -> 3.4357 | AB4: =R4/S4 -> 7.31 | AC4: =R4*T4 -> 0 | AD4: =R4-(R4*T4) -> 14.62
A5: 4 | B5: US-2015-108966 | C5: 42288 | D5: 42295 | E5: Standard Class | F5: SO-20335 | G5: Sean O'Donnell | H5: Consumer | I5: United States | J5: Fort Lauderdale | K5: Florida | L5: 33311 | M5: South | N5: FUR-TA-10000577 | O5: Furniture | P5: Tables | Q5: Bretford CR4500 Series Slim Rectangular Table | R5: 957.5775 | S5: 5 | T5: 0.45 | U5: -383.031 | V5: =YEAR(C5) -> 2015 | W5: =TEXT(C5,"mmm") -> Oct | X5: =Sample___Superstore[[#This Row],[Order Year]]&"-"&Sample___Superstore[[#This Row],[Order Month]] -> 2015-Oct | Y5: =Sample___Superstore6[[#This Row],[Profit]]/Sample___Superstore6[[#This Row],[Sales]] -> -0.4 | Z5: =D5-C5 -> 7 | AA5: =U5/S5 -> -76.6062 | AB5: =R5/S5 -> 191.5155 | AC5: =R5*T5 -> 430.90987 | AD5: =R5-(R5*T5) -> 526.66763
A6: 5 | B6: US-2015-108966 | C6: 42288 | D6: 42295 | E6: Standard Class | F6: SO-20335 | G6: Sean O'Donnell | H6: Consumer | I6: United States | J6: Fort Lauderdale | K6: Florida | L6: 33311 | M6: South | N6: OFF-ST-10000760 | O6: Office Supplies | P6: Storage | Q6: Eldon Fold 'N Roll Cart System | R6: 22.368 | S6: 2 | T6: 0.2 | U6: 2.5164 | V6: =YEAR(C6) -> 2015 | W6: =TEXT(C6,"mmm") -> Oct | X6: =Sample___Superstore[[#This Row],[Order Year]]&"-"&Sample___Superstore[[#This Row],[Order Month]] -> 2015-Oct | Y6: =Sample___Superstore6[[#This Row],[Profit]]/Sample___Superstore6[[#This Row],[Sales]] -> 0.1125 | Z6: =D6-C6 -> 7 | AA6: =U6/S6 -> 1.2582 | AB6: =R6/S6 -> 11.184 | AC6: =R6*T6 -> 4.4736 | AD6: =R6-(R6*T6) -> 17.8944
A7: 6 | B7: CA-2014-115812 | C7: 41799 | D7: 41804 | E7: Standard Class | F7: BH-11710 | G7: Brosina Hoffman | H7: Consumer | I7: United States | J7: Los Angeles | K7: California | L7: 90032 | M7: West | N7: FUR-FU-10001487 | O7: Furniture | P7: Furnishings | Q7: Eldon Expressions Wood and Plastic Desk Accessories, Cherry Wood | R7: 48.86 | S7: 7 | T7: 0 | U7: 14.1694 | V7: =YEAR(C7) -> 2014 | W7: =TEXT(C7,"mmm") -> Jun | X7: =Sample___Superstore[[#This Row],[Order Year]]&"-"&Sample___Superstore[[#This Row],[Order Month]] -> 2014-Jun | Y7: =Sample___Superstore6[[#This Row],[Profit]]/Sample___Superstore6[[#This Row],[Sales]] -> 0.29 | Z7: =D7-C7 -> 5 | AA7: =U7/S7 -> 2.0242 | AB7: =R7/S7 -> 6.98 | AC7: =R7*T7 -> 0 | AD7: =R7-(R7*T7) -> 48.86
A8: 7 | B8: CA-2014-115812 | C8: 41799 | D8: 41804 | E8: Standard Class | F8: BH-11710 | G8: Brosina Hoffman | H8: Consumer | I8: United States | J8: Los Angeles | K8: California | L8: 90032 | M8: West | N8: OFF-AR-10002833 | O8: Office Supplies | P8: Art | Q8: Newell 322 | R8: 7.28 | S8: 4 | T8: 0 | U8: 1.9656 | V8: =YEAR(C8) -> 2014 | W8: =TEXT(C8,"mmm") -> Jun | X8: =Sample___Superstore[[#This Row],[Order Year]]&"-"&Sample___Superstore[[#This Row],[Order Month]] -> 2014-Jun | Y8: =Sample___Superstore6[[#This Row],[Profit]]/Sample___Superstore6[[#This Row],[Sales]] -> 0.27 | Z8: =D8-C8 -> 5 | AA8: =U8/S8 -> 0.4914 | AB8: =R8/S8 -> 1.82 | AC8: =R8*T8 -> 0 | AD8: =R8-(R8*T8) -> 7.28
A9: 8 | B9: CA-2014-115812 | C9: 41799 | D9: 41804 | E9: Standard Class | F9: BH-11710 | G9: Brosina Hoffman | H9: Consumer | I9: United States | J9: Los Angeles | K9: California | L9: 90032 | M9: West | N9: TEC-PH-10002275 | O9: Technology | P9: Phones | Q9: Mitel 5320 IP Phone VoIP phone | R9: 907.152 | S9: 6 | T9: 0.2 | U9: 90.7152 | V9: =YEAR(C9) -> 2014 | W9: =TEXT(C9,"mmm") -> Jun | X9: =Sample___Superstore[[#This Row],[Order Year]]&"-"&Sample___Superstore[[#This Row],[Order Month]] -> 2014-Jun | Y9: =Sample___Superstore6[[#This Row],[Profit]]/Sample___Superstore6[[#This Row],[Sales]] -> 0.1 | Z9: =D9-C9 -> 5 | AA9: =U9/S9 -> 15.1192 | AB9: =R9/S9 -> 151.192 | AC9: =R9*T9 -> 181.4304 | AD9: =R9-(R9*T9) -> 725.7216
A10: 9 | B10: CA-2014-115812 | C10: 41799 | D10: 41804 | E10: Standard Class | F10: BH-11710 | G10: Brosina Hoffman | H10: Consumer | I10: United States | J10: Los Angeles | K10: California | L10: 90032 | M10: West | N10: OFF-BI-10003910 | O10: Office Supplies | P10: Binders | Q10: DXL Angle-View Binders with Locking Rings by Samsill | R10: 18.504 | S10: 3 | T10: 0.2 | U10: 5.7825 | V10: =YEAR(C10) -> 2014 | W10: =TEXT(C10,"mmm") -> Jun | X10: =Sample___Superstore[[#This Row],[Order Year]]&"-"&Sample___Superstore[[#This Row],[Order Month]] -> 2014-Jun | Y10: =Sample___Superstore6[[#This Row],[Profit]]/Sample___Superstore6[[#This Row],[Sales]] -> 0.3125 | Z10: =D10-C10 -> 5 | AA10: =U10/S10 -> 1.9275 | AB10: =R10/S10 -> 6.168 | AC10: =R10*T10 -> 3.7008 | AD10: =R10-(R10*T10) -> 14.8032
A11: 10 | B11: CA-2014-115812 | C11: 41799 | D11: 41804 | E11: Standard Class | F11: BH-11710 | G11: Brosina Hoffman | H11: Consumer | I11: United States | J11: Los Angeles | K11: California | L11: 90032 | M11: West | N11: OFF-AP-10002892 | O11: Office Supplies | P11: Appliances | Q11: Belkin F5C206VTEL 6 Outlet Surge | R11: 114.9 | S11: 5 | T11: 0 | U11: 34.47 | V11: =YEAR(C11) -> 2014 | W11: =TEXT(C11,"mmm") -> Jun | X11: =Sample___Superstore[[#This Row],[Order Year]]&"-"&Sample___Superstore[[#This Row],[Order Month]] -> 2014-Jun | Y11: =Sample___Superstore6[[#This Row],[Profit]]/Sample___Superstore6[[#This Row],[Sales]] -> 0.3 | Z11: =D11-C11 -> 5 | AA11: =U11/S11 -> 6.894 | AB11: =R11/S11 -> 22.98 | AC11: =R11*T11 -> 0 | AD11: =R11-(R11*T11) -> 114.9
A12: 11 | B12: CA-2014-115812 | C12: 41799 | D12: 41804 | E12: Standard Class | F12: BH-11710 | G12: Brosina Hoffman | H12: Consumer | I12: United States | J12: Los Angeles | K12: California | L12: 90032 | M12: West | N12: FUR-TA-10001539 | O12: Furniture | P12: Tables | Q12: Chromcraft Rectangular Conference Tables | R12: 1706.184 | S12: 9 | T12: 0.2 | U12: 85.3092 | V12: =YEAR(C12) -> 2014 | W12: =TEXT(C12,"mmm") -> Jun | X12: =Sample___Superstore[[#This Row],[Order Year]]&"-"&Sample___Superstore[[#This Row],[Order Month]] -> 2014-Jun | Y12: =Sample___Superstore6[[#This Row],[Profit]]/Sample___Superstore6[[#This Row],[Sales]] -> 0.05 | Z12: =D12-C12 -> 5 | AA12: =U12/S12 -> 9.4788 | AB12: =R12/S12 -> 189.576 | AC12: =R12*T12 -> 341.2368 | AD12: =R12-(R12*T12) -> 1364.9472
A13: 12 | B13: CA-2014-115812 | C13: 41799 | D13: 41804 | E13: Standard Class | F13: BH-11710 | G13: Brosina Hoffman | H13: Consumer | I13: United States | J13: Los Angeles | K13: California | L13: 90032 | M13: West | N13: TEC-PH-10002033 | O13: Technology | P13: Phones | Q13: Konftel 250 Conference phone - Charcoal black | R13: 911.424 | S13: 4 | T13: 0.2 | U13: 68.3568 | V13: =YEAR(C13) -> 2014 | W13: =TEXT(C13,"mmm") -> Jun | X13: =Sample___Superstore[[#This Row],[Order Year]]&"-"&Sample___Superstore[[#This Row],[Order Month]] -> 2014-Jun | Y13: =Sample___Superstore6[[#This Row],[Profit]]/Sample___Superstore6[[#This Row],[Sales]] -> 0.075 | Z13: =D13-C13 -> 5 | AA13: =U13/S13 -> 17.0892 | AB13: =R13/S13 -> 227.856 | AC13: =R13*T13 -> 182.2848 | AD13: =R13-(R13*T13) -> 729.1392
... A182: 181 | B182: CA-2014-166191 | C182: 41978 | D182: 41982 | E182: Second Class | F182: DK-13150 | G182: David Kendrick | H182: Corporate | I182: United States | J182: Decatur | K182: Illinois | L182: 62521 | M182: Central | N182: OFF-ST-10003455 | O182: Office Supplies | P182: Storage | Q182: Tenex File Box, Personal Filing Tote with Lid, Black | R182: 24.816 | S182: 2 | T182: 0.2 | U182: 1.8612 | V182: =YEAR(C182) -> 2014 | W182: =TEXT(C182,"mmm") -> Dec | X182: =Sample___Superstore[[#This Row],[Order Year]]&"-"&Sample___Superstore[[#This Row],[Order Month]] -> 2014-Dec | Y182: =Sample___Superstore6[[#This Row],[Profit]]/Sample___Superstore6[[#This Row],[Sales]] -> 0.075 | Z182: =D182-C182 -> 4 | AA182: =U182/S182 -> 0.9306 | AB182: =R182/S182 -> 12.408 | AC182: =R182*T182 -> 4.9632 | AD182: =R182-(R182*T182) -> 19.8528
A183: 182 | B183: CA-2014-166191 | C183: 41978 | D183: 41982 | E183: Second Class | F183: DK-13150 | G183: David Kendrick | H183: Corporate | I183: United States | J183: Decatur | K183: Illinois | L183: 62521 | M183: Central | N183: TEC-AC-10004659 | O183: Technology | P183: Accessories | Q183: Imation Secure+ Hardware Encrypted USB 2.0 Flash Drive | V183: =YEAR(C183) -> 2014 | W183: =TEXT(C183,"mmm") -> Dec | X183: =Sample___Superstore[[#This Row],[Order Year]]&"-"&Sample___Superstore[[#This Row],[Order Month]] -> 2014-Dec | Y183: =Sample___Superstore6[[#This Row],[Profit]]/Sample___Superstore6[[#This Row],[Sales]] -> #DIV/0! | Z183: =D183-C183 -> 4 | AA183: =U183/S183 -> #DIV/0! | AB183: =R183/S183 -> #DIV/0! | AC183: =R183*T183 -> 0 | AD183: =R183-(R183*T183) -> 0
A184: 183 | B184: CA-2014-158274 | C184: 41962 | D184: 41967 | E184: Second Class | F184: RM-19675 | G184: Robert Marley | H184: Home Office | I184: United States | J184: Monroe | K184: Louisiana | L184: 71203 | M184: South | N184: TEC-PH-10003273 | O184: Technology | P184: Phones | Q184: AT&T TR1909W | R184: 503.96 | S184: 4 | T184: 0 | U184: 131.0296 | V184: =YEAR(C184) -> 2014 | W184: =TEXT(C184,"mmm") -> Nov | X184: =Sample___Superstore[[#This Row],[Order Year]]&"-"&Sample___Superstore[[#This Row],[Order Month]] -> 2014-Nov | Y184: =Sample___Superstore6[[#This Row],[Profit]]/Sample___Superstore6[[#This Row],[Sales]] -> 0.26 | Z184: =D184-C184 -> 5 | AA184: =U184/S184 -> 32.7574 | AB184: =R184/S184 -> 125.99 | AC184: =R184*T184 -> 0 | AD184: =R184-(R184*T184) -> 503.96
A185: 184 | B185: CA-2014-158274 | C185: 41962 | D185: 41967 | E185: Second Class | F185: RM-19675 | G185: Robert Marley | H185: Home Office | I185: United States | J185: Monroe | K185: Louisiana | L185: 71203 | M185: South | N185: TEC-PH-10004896 | O185: Technology | P185: Phones | Q185: Nokia Lumia 521 (T-Mobile) | R185: 149.95 | S185: 5 | T185: 0 | U185: 41.986 | V185: =YEAR(C185) -> 2014 | W185: =TEXT(C185,"mmm") -> Nov | X185: =Sample___Superstore[[#This Row],[Order Year]]&"-"&Sample___Superstore[[#This Row],[Order Month]] -> 2014-Nov | Y185: =Sample___Superstore6[[#This Row],[Profit]]/Sample___Superstore6[[#This Row],[Sales]] -> 0.28 | Z185: =D185-C185 -> 5 | AA185: =U185/S185 -> 8.3972 | AB185: =R185/S185 -> 29.99 | AC185: =R185*T185 -> 0 | AD185: =R185-(R185*T185) -> 149.95
A186: 185 | B186: CA-2014-158274 | C186: 41962 | D186: 41967 | E186: Second Class | F186: RM-19675 | G186: Robert Marley | H186: Home Office | I186: United States | J186: Monroe | K186: Louisiana | L186: 71203 | M186: South | N186: TEC-AC-10002345 | O186: Technology | P186: Accessories | Q186: HP Standard 104 key PS/2 Keyboard | R186: 29 | S186: 2 | T186: 0 | U186: 7.25 | V186: =YEAR(C186) -> 2014 | W186: =TEXT(C186,"mmm") -> Nov | X186: =Sample___Superstore[[#This Row],[Order Year]]&"-"&Sample___Superstore[[#This Row],[Order Month]] -> 2014-Nov | Y186: =Sample___Superstore6[[#This Row],[Profit]]/Sample___Superstore6[[#This Row],[Sales]] -> 0.25 | Z186: =D186-C186 -> 5 | AA186: =U186/S186 -> 3.625 | AB186: =R186/S186 -> 14.5 | AC186: =R186*T186 -> 0 | AD186: =R186-(R186*T186) -> 29
A187: 186 | B187: CA-2016-105018 | C187: 42702 | D187: 42706 | E187: Standard Class | F187: SK-19990 | G187: Sally Knutson | H187: Consumer | I187: United States | J187: Fairfield | K187: Connecticut | L187: 6824 | M187: East | N187: OFF-BI-10001890 | O187: Office Supplies | P187: Binders | Q187: Avery Poly Binder Pockets | R187: 7.16 | S187: 2 | T187: 0 | U187: 3.4368 | V187: =YEAR(C187) -> 2016 | W187: =TEXT(C187,"mmm") -> Nov | X187: =Sample___Superstore[[#This Row],[Order Year]]&"-"&Sample___Superstore[[#This Row],[Order Month]] -> 2016-Nov | Y187: =Sample___Superstore6[[#This Row],[Profit]]/Sample___Superstore6[[#This Row],[Sales]] -> 0.48 | Z187: =D187-C187 -> 4 | AA187: =U187/S187 -> 1.7184 | AB187: =R187/S187 -> 3.58 | AC187: =R187*T187 -> 0 | AD187: =R187-(R187*T187) -> 7.16
A188: 187 | B188: CA-2014-123260 | C188: 41877 | D188: 41881 | E188: Standard Class | F188: FM-14290 | G188: Frank Merwin | H188: Home Office | I188: United States | J188: Los Angeles | K188: California | L188: 90032 | M188: West | N188: TEC-AC-10002323 | O188: Technology | P188: Accessories | Q188: SanDisk Ultra 32 GB MicroSDHC Class 10 Memory Card | R188: 176.8 | S188: 8 | T188: 0 | U188: 22.984 | V188: =YEAR(C188) -> 2014 | W188: =TEXT(C188,"mmm") -> Aug | X188: =Sample___Superstore[[#This Row],[Order Year]]&"-"&Sample___Superstore[[#This Row],[Order Month]] -> 2014-Aug | Y188: =Sample___Superstore6[[#This Row],[Profit]]/Sample___Superstore6[[#This Row],[Sales]] -> 0.13 | Z188: =D188-C188 -> 4 | AA188: =U188/S188 -> 2.873 | AB188: =R188/S188 -> 22.1 | AC188: =R188*T188 -> 0 | AD188: =R188-(R188*T188) -> 176.8
A189: 188 | B189: CA-2016-157000 | C189: 42567 | D189: 42573 | E189: Standard Class | F189: AM-10360 | G189: Alice McCarthy | H189: Corporate | I189: United States | J189: Grand Prairie | K189: Texas | L189: 75051 | M189: Central | N189: OFF-ST-10001328 | O189: Office Supplies | P189: Storage | Q189: Personal Filing Tote with Lid, Black/Gray | R189: 37.224 | S189: 3 | T189: 0.2 | U189: 3.7224 | V189: =YEAR(C189) -> 2016 | W189: =TEXT(C189,"mmm") -> Jul | X189: =Sample___Superstore[[#This Row],[Order Year]]&"-"&Sample___Superstore[[#This Row],[Order Month]] -> 2016-Jul | Y189: =Sample___Superstore6[[#This Row],[Profit]]/Sample___Superstore6[[#This Row],[Sales]] -> 0.1 | Z189: =D189-C189 -> 6 | AA189: =U189/S189 -> 1.2408 | AB189: =R189/S189 -> 12.408 | AC189: =R189*T189 -> 7.4448 | AD189: =R189-(R189*T189) -> 29.7792
A190: 189 | B190: CA-2016-157000 | C190: 42567 | D190: 42573 | E190: Standard Class | F190: AM-10360 | G190: Alice McCarthy | H190: Corporate | I190: United States | J190: Grand Prairie | K190: Texas | L190: 75051 | M190: Central | N190: OFF-PA-10001950 | O190: Office Supplies | P190: Paper | Q190: Southworth 25% Cotton Antique Laid Paper & Envelopes | R190: 20.016 | S190: 3 | T190: 0.2 | U190: 6.255 | V190: =YEAR(C190) -> 2016 | W190: =TEXT(C190,"mmm") -> Jul | X190: =Sample___Superstore[[#This Row],[Order Year]]&"-"&Sample___Superstore[[#This Row],[Order Month]] -> 2016-Jul | Y190: =Sample___Superstore6[[#This Row],[Profit]]/Sample___Superstore6[[#This Row],[Sales]] -> 0.3125 | Z190: =D190-C190 -> 6 | AA190: =U190/S190 -> 2.085 | AB190: =R190/S190 -> 6.672 | AC190: =R190*T190 -> 4.0032 | AD190: =R190-(R190*T190) -> 16.0128
A191: 190 | B191: CA-2015-102281 | C191: 42289 | D191: 42291 | E191: First Class | F191: MP-17470 | G191: Mark Packer | H191: Home Office | I191: United States | J191: New York City | K191: New York | L191: 10035 | M191: East | N191: FUR-BO-10002613 | O191: Furniture | P191: Bookcases | Q191: Atlantic Metals Mobile 4-Shelf Bookcases, Custom Colors | R191: 899.136 | S191: 4 | T191: 0.2 | U191: 112.392 | V191: =YEAR(C191) -> 2015 | W191: =TEXT(C191,"mmm") -> Oct | X191: =Sample___Superstore[[#This Row],[Order Year]]&"-"&Sample___Superstore[[#This Row],[Order Month]] -> 2015-Oct | Y191: =Sample___Superstore6[[#This Row],[Profit]]/Sample___Superstore6[[#This Row],[Sales]] -> 0.125 | Z191: =D191-C191 -> 2 | AA191: =U191/S191 -> 28.098 | AB191: =R191/S191 -> 224.784 | AC191: =R191*T191 -> 179.8272 | AD191: =R191-(R191*T191) -> 719.3088
A192: 191 | B192: CA-2015-102281 | C192: 42289 | D192: 42291 | E192: First Class | F192: MP-17470 | G192: Mark Packer | H192: Home Office | I192: United States | J192: New York City | K192: New York | L192: 10035 | M192: East | N192: TEC-PH-10001552 | O192: Technology | P192: Phones | Q192: I Need's 3d Hello Kitty Hybrid Silicone Case Cover for HTC One X 4g with 3d Hello Kitty Stylus Pen Green/pink | R192: 71.76 | S192: 6 | T192: 0 | U192: 20.0928 | V192: =YEAR(C192) -> 2015 | W192: =TEXT(C192,"mmm") -> Oct | X192: =Sample___Superstore[[#This Row],[Order Year]]&"-"&Sample___Superstore[[#This Row],[Order Month]] -> 2015-Oct | Y192: =Sample___Superstore6[[#This Row],[Profit]]/Sample___Superstore6[[#This Row],[Sales]] -> 0.28 | Z192: =D192-C192 -> 2 | AA192: =U192/S192 -> 3.3488 | AB192: =R192/S192 -> 11.96 | AC192: =R192*T192 -> 0 | AD192: =R192-(R192*T192) -> 71.76
A193: 192 | B193: CA-2015-102281 | C193: 42289 | D193: 42291 | E193: First Class | F193: MP-17470 | G193: Mark Packer | H193: Home Office | I193: United States | J193: New York City | K193: New York | L193: 10035 | M193: East | N193: OFF-PA-10000061 | O193: Office Supplies | P193: Paper | Q193: Xerox 205 | R193: 51.84 | S193: 8 | T193: 0 | U193: 24.8832 | V193: =YEAR(C193) -> 2015 | W193: =TEXT(C193,"mmm") -> Oct | X193: =Sample___Superstore[[#This Row],[Order Year]]&"-"&Sample___Superstore[[#This Row],[Order Month]] -> 2015-Oct | Y193: =Sample___Superstore6[[#This Row],[Profit]]/Sample___Superstore6[[#This Row],[Sales]] -> 0.48 | Z193: =D193-C193 -> 2 | AA193: =U193/S193 -> 3.1104 | AB193: =R193/S193 -> 6.48 | AC193: =R193*T193 -> 0 | AD193: =R193-(R193*T193) -> 51.84
A194: 193 | B194: CA-2015-102281 | C194: 42289 | D194: 42291 | E194: First Class | F194: MP-17470 | G194: Mark Packer | H194: Home Office | I194: United States | J194: New York City | K194: New York | L194: 10035 | M194: East | N194: FUR-BO-10002545 | O194: Furniture | P194: Bookcases | Q194: Atlantic Metals Mobile 3-Shelf Bookcases, Custom Colors | R194: 626.352 | S194: 3 | T194: 0.2 | U194: 46.9764 | V194: =YEAR(C194) -> 2015 | W194: =TEXT(C194,"mmm") -> Oct | X194: =Sample___Superstore[[#This Row],[Order Year]]&"-"&Sample___Superstore[[#This Row],[Order Month]] -> 2015-Oct | Y194: =Sample___Superstore6[[#This Row],[Profit]]/Sample___Superstore6[[#This Row],[Sales]] -> 0.075 | Z194: =D194-C194 -> 2 | AA194: =U194/S194 -> 15.6588 | AB194: =R194/S194 -> 208.784 | AC194: =R194*T194 -> 125.2704 | AD194: =R194-(R194*T194) -> 501.0816
A195: 194 | B195: CA-2015-102281 | C195: 42289 | D195: 42291 | E195: First Class | F195: MP-17470 | G195: Mark Packer | H195: Home Office | I195: United States | J195: New York City | K195: New York | L195: 10035 | M195: East | N195: OFF-AR-10003514 | O195: Office Supplies | P195: Art | Q195: 4009 Highlighters by Sanford | R195: 19.9 | S195: 5 | T195: 0 | U195: 6.567 | V195: =YEAR(C195) -> 2015 | W195: =TEXT(C195,"mmm") -> Oct | X195: =Sample___Superstore[[#This Row],[Order Year]]&"-"&Sample___Superstore[[#This Row],[Order Month]] -> 2015-Oct | Y195: =Sample___Superstore6[[#This Row],[Profit]]/Sample___Superstore6[[#This Row],[Sales]] -> 0.33 | Z195: =D195-C195 -> 2 | AA195: =U195/S195 -> 1.3134 | AB195: =R195/S195 -> 3.98 | AC195: =R195*T195 -> 0 | AD195: =R195-(R195*T195) -> 19.9
... A431: 430 | B431: US-2016-123750 | C431: 42475 | D431: 42481 | E431: Standard Class | F431: RB-19795 | G431: Ross Baird | H431: Home Office | I431: United States | J431: Gastonia | K431: North Carolina | L431: 28052 | M431: South | N431: OFF-BI-10004584 | O431: Office Supplies | P431: Binders | Q431: GBC ProClick 150 Presentation Binding System | R431: 189.588 | S431: 2 | T431: 0.7 | U431: -145.3508 | V431: =YEAR(C431) -> 2016 | W431: =TEXT(C431,"mmm") -> Apr | X431: =Sample___Superstore[[#This Row],[Order Year]]&"-"&Sample___Superstore[[#This Row],[Order Month]] -> 2016-Apr | Y431: =Sample___Superstore6[[#This Row],[Profit]]/Sample___Superstore6[[#This Row],[Sales]] -> -0.76666667 | Z431: =D431-C431 -> 6 | AA431: =U431/S431 -> -72.6754 | AB431: =R431/S431 -> 94.794 | AC431: =R431*T431 -> 132.7116 | AD431: =R431-(R431*T431) -> 56.8764
A432: 431 | B432: US-2016-123750 | C432: 42475 | D432: 42481 | E432: Standard Class | F432: RB-19795 | G432: Ross Baird | H432: Home Office | I432: United States | J432: Gastonia | K432: North Carolina | L432: 28052 | M432: South | N432: TEC-AC-10004659 | O432: Technology | P432: Accessories | Q432: Imation Secure+ Hardware Encrypted USB 2.0 Flash Drive | V432: =YEAR(C432) -> 2016 | W432: =TEXT(C432,"mmm") -> Apr | X432: =Sample___Superstore[[#This Row],[Order Year]]&"-"&Sample___Superstore[[#This Row],[Order Month]] -> 2016-Apr | Y432: =Sample___Superstore6[[#This Row],[Profit]]/Sample___Superstore6[[#This Row],[Sales]] -> #DIV/0! | Z432: =D432-C432 -> 6 | AA432: =U432/S432 -> #DIV/0! | AB432: =R432/S432 -> #DIV/0! | AC432: =R432*T432 -> 0 | AD432: =R432-(R432*T432) -> 0
A433: 432 | B433: US-2016-123750 | C433: 42475 | D433: 42481 | E433: Standard Class | F433: RB-19795 | G433: Ross Baird | H433: Home Office | I433: United States | J433: Gastonia | K433: North Carolina | L433: 28052 | M433: South | N433: TEC-AC-10004659 | O433: Technology | P433: Accessories | Q433: Imation Secure+ Hardware Encrypted USB 2.0 Flash Drive | V433: =YEAR(C433) -> 2016 | W433: =TEXT(C433,"mmm") -> Apr | X433: =Sample___Superstore[[#This Row],[Order Year]]&"-"&Sample___Superstore[[#This Row],[Order Month]] -> 2016-Apr | Y433: =Sample___Superstore6[[#This Row],[Profit]]/Sample___Superstore6[[#This Row],[Sales]] -> #DIV/0! | Z433: =D433-C433 -> 6 | AA433: =U433/S433 -> #DIV/0! | AB433: =R433/S433 -> #DIV/0! | AC433: =R433*T433 -> 0 | AD433: =R433-(R433*T433) -> 0
A434: 433 | B434: US-2016-123750 | C434: 42475 | D434: 42481 | E434: Standard Class | F434: RB-19795 | G434: Ross Baird | H434: Home Office | I434: United States | J434: Gastonia | K434: North Carolina | L434: 28052 | M434: South | N434: OFF-ST-10000617 | O434: Office Supplies | P434: Storage | Q434: Woodgrain Magazine Files by Perma | R434: 4.768 | S434: 2 | T434: 0.2 | U434: -0.7748 | V434: =YEAR(C434) -> 2016 | W434: =TEXT(C434,"mmm") -> Apr | X434: =Sample___Superstore[[#This Row],[Order Year]]&"-"&Sample___Superstore[[#This Row],[Order Month]] -> 2016-Apr | Y434: =Sample___Superstore6[[#This Row],[Profit]]/Sample___Superstore6[[#This Row],[Sales]] -> -0.1625 | Z434: =D434-C434 -> 6 | AA434: =U434/S434 -> -0.3874 | AB434: =R434/S434 -> 2.384 | AC434: =R434*T434 -> 0.9536 | AD434: =R434-(R434*T434) -> 3.8144
A435: 434 | B435: CA-2016-127369 | C435: 42527 | D435: 42528 | E435: First Class | F435: DB-13060 | G435: Dave Brooks | H435: Consumer | I435: United States | J435: Lowell | K435: Massachusetts | L435: 1852 | M435: East | N435: OFF-ST-10003306 | O435: Office Supplies | P435: Storage | Q435: Letter Size Cart | R435: 714.3 | S435: 5 | T435: 0 | U435: 207.147 | V435: =YEAR(C435) -> 2016 | W435: =TEXT(C435,"mmm") -> Jun | X435: =Sample___Superstore[[#This Row],[Order Year]]&"-"&Sample___Superstore[[#This Row],[Order Month]] -> 2016-Jun | Y435: =Sample___Superstore6[[#This Row],[Profit]]/Sample___Superstore6[[#This Row],[Sales]] -> 0.29 | Z435: =D435-C435 -> 1 | AA435: =U435/S435 -> 41.4294 | AB435: =R435/S435 -> 142.86 | AC435: =R435*T435 -> 0 | AD435: =R435-(R435*T435) -> 714.3
A436: 435 | B436: US-2014-150574 | C436: 41992 | D436: 41998 | E436: Standard Class | F436: MK-18160 | G436: Mike Kennedy | H436: Consumer | I436: United States | J436: Jacksonville | K436: Florida | L436: 32216 | M436: South | N436: OFF-BI-10000773 | O436: Office Supplies | P436: Binders | Q436: Insertable Tab Post Binder Dividers | R436: 4.812 | S436: 2 | T436: 0.7 | U436: -3.6892 | V436: =YEAR(C436) -> 2014 | W436: =TEXT(C436,"mmm") -> Dec | X436: =Sample___Superstore[[#This Row],[Order Year]]&"-"&Sample___Superstore[[#This Row],[Order Month]] -> 2014-Dec | Y436: =Sample___Superstore6[[#This Row],[Profit]]/Sample___Superstore6[[#This Row],[Sales]] -> -0.76666667 | Z436: =D436-C436 -> 6 | AA436: =U436/S436 -> -1.8446 | AB436: =R436/S436 -> 2.406 | AC436: =R436*T436 -> 3.3684 | AD436: =R436-(R436*T436) -> 1.4436
A437: 436 | B437: US-2014-150574 | C437: 41992 | D437: 41998 | E437: Standard Class | F437: MK-18160 | G437: Mike Kennedy | H437: Consumer | I437: United States | J437: Jacksonville | K437: Florida | L437: 32216 | M437: South | N437: TEC-AC-10002600 | O437: Technology | P437: Accessories | Q437: Belkin QODE FastFit Bluetooth Keyboard | R437: 247.8 | S437: 5 | T437: 0.2 | U437: -18.585 | V437: =YEAR(C437) -> 2014 | W437: =TEXT(C437,"mmm") -> Dec | X437: =Sample___Superstore[[#This Row],[Order Year]]&"-"&Sample___Superstore[[#This Row],[Order Month]] -> 2014-Dec | Y437: =Sample___Superstore6[[#This Row],[Profit]]/Sample___Superstore6[[#This Row],[Sales]] -> -0.075 | Z437: =D437-C437 -> 6 | AA437: =U437/S437 -> -3.717 | AB437: =R437/S437 -> 49.56 | AC437: =R437*T437 -> 49.56 | AD437: =R437-(R437*T437) -> 198.24
A438: 437 | B438: CA-2016-147375 | C438: 42533 | D438: 42535 | E438: Second Class | F438: PO-19180 | G438: Philisse Overcash | H438: Home Office | I438: United States | J438: Chicago | K438: Illinois | L438: 60623 | M438: Central | N438: TEC-MA-10002937 | O438: Technology | P438: Machines | Q438: Canon Color ImageCLASS MF8580Cdw Wireless Laser All-In-One Printer, Copier, Scanner | R438: 1007.979 | S438: 3 | T438: 0.3 | U438: 43.1991 | V438: =YEAR(C438) -> 2016 | W438: =TEXT(C438,"mmm") -> Jun | X438: =Sample___Superstore[[#This Row],[Order Year]]&"-"&Sample___Superstore[[#This Row],[Order Month]] -> 2016-Jun | Y438: =Sample___Superstore6[[#This Row],[Profit]]/Sample___Superstore6[[#This Row],[Sales]] -> 0.042857143 | Z438: =D438-C438 -> 2 | AA438: =U438/S438 -> 14.3997 | AB438: =R438/S438 -> 335.993 | AC438: =R438*T438 -> 302.3937 | AD438: =R438-(R438*T438) -> 705.5853
A439: 438 | B439: CA-2016-147375 | C439: 42533 | D439: 42535 | E439: Second Class | F439: PO-19180 | G439: Philisse Overcash | H439: Home Office | I439: United States | J439: Chicago | K439: Illinois | L439: 60623 | M439: Central | N439: OFF-PA-10001970 | O439: Office Supplies | P439: Paper | Q439: Xerox 1908 | R439: 313.488 | S439: 7 | T439: 0.2 | U439: 113.6394 | V439: =YEAR(C439) -> 2016 | W439: =TEXT(C439,"mmm") -> Jun | X439: =Sample___Superstore[[#This Row],[Order Year]]&"-"&Sample___Superstore[[#This Row],[Order Month]] -> 2016-Jun | Y439: =Sample___Superstore6[[#This Row],[Profit]]/Sample___Superstore6[[#This Row],[Sales]] -> 0.3625 | Z439: =D439-C439 -> 2 | AA439: =U439/S439 -> 16.2342 | AB439: =R439/S439 -> 44.784 | AC439: =R439*T439 -> 62.6976 | AD439: =R439-(R439*T439) -> 250.7904
A440: 439 | B440: CA-2017-130043 | C440: 42993 | D440: 42997 | E440: Standard Class | F440: BB-11545 | G440: Brenda Bowman | H440: Corporate | I440: United States | J440: Houston | K440: Texas | L440: 77070 | M440: Central | N440: OFF-PA-10002230 | O440: Office Supplies | P440: Paper | Q440: Xerox 1897 | R440: 31.872 | S440: 8 | T440: 0.2 | U440: 11.5536 | V440: =YEAR(C440) -> 2017 | W440: =TEXT(C440,"mmm") -> Sep | X440: =Sample___Superstore[[#This Row],[Order Year]]&"-"&Sample___Superstore[[#This Row],[Order Month]] -> 2017-Sep | Y440: =Sample___Superstore6[[#This Row],[Profit]]/Sample___Superstore6[[#This Row],[Sales]] -> 0.3625 | Z440: =D440-C440 -> 4 | AA440: =U440/S440 -> 1.4442 | AB440: =R440/S440 -> 3.984 | AC440: =R440*T440 -> 6.3744 | AD440: =R440-(R440*T440) -> 25.4976
A441: 440 | B441: CA-2017-157252 | C441: 42755 | D441: 42758 | E441: Second Class | F441: CV-12805 | G441: Cynthia Voltz | H441: Corporate | I441: United States | J441: New York City | K441: New York | L441: 10024 | M441: East | N441: FUR-CH-10003396 | O441: Furniture | P441: Chairs | Q441: Global Deluxe Steno Chair | R441: 207.846 | S441: 3 | T441: 0.1 | U441: 2.3094 | V441: =YEAR(C441) -> 2017 | W441: =TEXT(C441,"mmm") -> Jan | X441: =Sample___Superstore[[#This Row],[Order Year]]&"-"&Sample___Superstore[[#This Row],[Order Month]] -> 2017-Jan | Y441: =Sample___Superstore6[[#This Row],[Profit]]/Sample___Superstore6[[#This Row],[Sales]] -> 0.011111111 | Z441: =D441-C441 -> 3 | AA441: =U441/S441 -> 0.7698 | AB441: =R441/S441 -> 69.282 | AC441: =R441*T441 -> 20.7846 | AD441: =R441-(R441*T441) -> 187.0614
A442: 441 | B442: CA-2016-115756 | C442: 42618 | D442: 42620 | E442: Second Class | F442: PK-19075 | G442: Pete Kriz | H442: Consumer | I442: United States | J442: Detroit | K442: Michigan | L442: 48227 | M442: Central | N442: FUR-FU-10000246 | O442: Furniture | P442: Furnishings | Q442: Aluminum Document Frame | R442: 12.22 | S442: 1 | T442: 0 | U442: 3.666 | V442: =YEAR(C442) -> 2016 | W442: =TEXT(C442,"mmm") -> Sep | X442: =Sample___Superstore[[#This Row],[Order Year]]&"-"&Sample___Superstore[[#This Row],[Order Month]] -> 2016-Sep | Y442: =Sample___Superstore6[[#This Row],[Profit]]/Sample___Superstore6[[#This Row],[Sales]] -> 0.3 | Z442: =D442-C442 -> 2 | AA442: =U442/S442 -> 3.666 | AB442: =R442/S442 -> 12.22 | AC442: =R442*T442 -> 0 | AD442: =R442-(R442*T442) -> 12.22
A443: 442 | B443: CA-2016-115756 | C443: 42618 | D443: 42620 | E443: Second Class | F443: PK-19075 | G443: Pete Kriz | H443: Consumer | I443: United States | J443: Detroit | K443: Michigan | L443: 48227 | M443: Central | N443: OFF-ST-10000060 | O443: Office Supplies | P443: Storage | Q443: Fellowes Bankers Box Staxonsteel Drawer File/Stacking System | R443: 194.94 | S443: 3 | T443: 0 | U443: 23.3928 | V443: =YEAR(C443) -> 2016 | W443: =TEXT(C443,"mmm") -> Sep | X443: =Sample___Superstore[[#This Row],[Order Year]]&"-"&Sample___Superstore[[#This Row],[Order Month]] -> 2016-Sep | Y443: =Sample___Superstore6[[#This Row],[Profit]]/Sample___Superstore6[[#This Row],[Sales]] -> 0.12 | Z443: =D443-C443 -> 2 | AA443: =U443/S443 -> 7.7976 | AB443: =R443/S443 -> 64.98 | AC443: =R443*T443 -> 0 | AD443: =R443-(R443*T443) -> 194.94
A444: 443 | B444: CA-2016-115756 | C444: 42618 | D444: 42620 | E444: Second Class | F444: PK-19075 | G444: Pete Kriz | H444: Consumer | I444: United States | J444: Detroit | K444: Michigan | L444: 48227 | M444: Central | N444: OFF-ST-10003058 | O444: Office Supplies | P444: Storage | Q444: Eldon Mobile Mega Data Cart Mega Stackable Add-On Trays | R444: 70.95 | S444: 3 | T444: 0 | U444: 20.5755 | V444: =YEAR(C444) -> 2016 | W444: =TEXT(C444,"mmm") -> Sep | X444: =Sample___Superstore[[#This Row],[Order Year]]&"-"&Sample___Superstore[[#This Row],[Order Month]] -> 2016-Sep | Y444: =Sample___Superstore6[[#This Row],[Profit]]/Sample___Superstore6[[#This Row],[Sales]] -> 0.29 | Z444: =D444-C444 -> 2 | AA444: =U444/S444 -> 6.8585 | AB444: =R444/S444 -> 23.65 | AC444: =R444*T444 -> 0 | AD444: =R444-(R444*T444) -> 70.95
A445: 444 | B445: CA-2016-115756 | C445: 42618 | D445: 42620 | E445: Second Class | F445: PK-19075 | G445: Pete Kriz | H445: Consumer | I445: United States | J445: Detroit | K445: Michigan | L445: 48227 | M445: Central | N445: OFF-PA-10002222 | O445: Office Supplies | P445: Paper | Q445: Xerox Color Copier Paper, 11" x 17", Ream | R445: 91.36 | S445: 4 | T445: 0 | U445: 42.0256 | V445: =YEAR(C445) -> 2016 | W445: =TEXT(C445,"mmm") -> Sep | X445: =Sample___Superstore[[#This Row],[Order Year]]&"-"&Sample___Superstore[[#This Row],[Order Month]] -> 2016-Sep | Y445: =Sample___Superstore6[[#This Row],[Profit]]/Sample___Superstore6[[#This Row],[Sales]] -> 0.46 | Z445: =D445-C445 -> 2 | AA445: =U445/S445 -> 10.5064 | AB445: =R445/S445 -> 22.84 | AC445: =R445*T445 -> 0 | AD445: =R445-(R445*T445) -> 91.36
... A1407: 1406 | B1407: US-2014-118486 | C1407: 41735 | D1407: 41737 | E1407: First Class | F1407: SD-20485 | G1407: Shirley Daniels | H1407: Home Office | I1407: United States | J1407: Philadelphia | K1407: Pennsylvania | L1407: 19143 | M1407: East | N1407: FUR-TA-10001039 | O1407: Furniture | P1407: Tables | Q1407: KI Adjustable-Height Table | R1407: 154.764 | S1407: 3 | T1407: 0.4 | U1407: -36.1116 | V1407: =YEAR(C1407) -> 2014 | W1407: =TEXT(C1407,"mmm") -> Apr | X1407: =Sample___Superstore[[#This Row],[Order Year]]&"-"&Sample___Superstore[[#This Row],[Order Month]] -> 2014-Apr | Y1407: =Sample___Superstore6[[#This Row],[Profit]]/Sample___Superstore6[[#This Row],[Sales]] -> -0.23333333 | Z1407: =D1407-C1407 -> 2 | AA1407: =U1407/S1407 -> -12.0372 | AB1407: =R1407/S1407 -> 51.588 | AC1407: =R1407*T1407 -> 61.9056 | AD1407: =R1407-(R1407*T1407) -> 92.8584
A1408: 1407 | B1408: US-2014-118486 | C1408: 41735 | D1408: 41737 | E1408: First Class | F1408: SD-20485 | G1408: Shirley Daniels | H1408: Home Office | I1408: United States | J1408: Philadelphia | K1408: Pennsylvania | L1408: 19143 | M1408: East | N1408: TEC-AC-10004659 | O1408: Technology | P1408: Accessories | Q1408: Imation Secure+ Hardware Encrypted USB 2.0 Flash Drive | V1408: =YEAR(C1408) -> 2014 | W1408: =TEXT(C1408,"mmm") -> Apr | X1408: =Sample___Superstore[[#This Row],[Order Year]]&"-"&Sample___Superstore[[#This Row],[Order Month]] -> 2014-Apr | Y1408: =Sample___Superstore6[[#This Row],[Profit]]/Sample___Superstore6[[#This Row],[Sales]] -> #DIV/0! | Z1408: =D1408-C1408 -> 2 | AA1408: =U1408/S1408 -> #DIV/0! | AB1408: =R1408/S1408 -> #DIV/0! | AC1408: =R1408*T1408 -> 0 | AD1408: =R1408-(R1408*T1408) -> 0
A1409: 1408 | B1409: CA-2016-130407 | C1409: 42615 | D1409: 42619 | E1409: Standard Class | F1409: KD-16270 | G1409: Karen Daniels | H1409: Consumer | I1409: United States | J1409: New York City | K1409: New York | L1409: 10024 | M1409: East | N1409: OFF-AR-10002240 | O1409: Office Supplies | P1409: Art | Q1409: Panasonic KP-150 Electric Pencil Sharpener | R1409: 75.48 | S1409: 2 | T1409: 0 | U1409: 19.6248 | V1409: =YEAR(C1409) -> 2016 | W1409: =TEXT(C1409,"mmm") -> Sep | X1409: =Sample___Superstore[[#This Row],[Order Year]]&"-"&Sample___Superstore[[#This Row],[Order Month]] -> 2016-Sep | Y1409: =Sample___Superstore6[[#This Row],[Profit]]/Sample___Superstore6[[#This Row],[Sales]] -> 0.26 | Z1409: =D1409-C1409 -> 4 | AA1409: =U1409/S1409 -> 9.8124 | AB1409: =R1409/S1409 -> 37.74 | AC1409: =R1409*T1409 -> 0 | AD1409: =R1409-(R1409*T1409) -> 75.48
A1410: 1409 | B1410: CA-2016-130407 | C1410: 42615 | D1410: 42619 | E1410: Standard Class | F1410: KD-16270 | G1410: Karen Daniels | H1410: Consumer | I1410: United States | J1410: New York City | K1410: New York | L1410: 10024 | M1410: East | N1410: FUR-FU-10001967 | O1410: Furniture | P1410: Furnishings | Q1410: Telescoping Adjustable Floor Lamp | R1410: 39.98 | S1410: 2 | T1410: 0 | U1410: 9.995 | V1410: =YEAR(C1410) -> 2016 | W1410: =TEXT(C1410,"mmm") -> Sep | X1410: =Sample___Superstore[[#This Row],[Order Year]]&"-"&Sample___Superstore[[#This Row],[Order Month]] -> 2016-Sep | Y1410: =Sample___Superstore6[[#This Row],[Profit]]/Sample___Superstore6[[#This Row],[Sales]] -> 0.25 | Z1410: =D1410-C1410 -> 4 | AA1410: =U1410/S1410 -> 4.9975 | AB1410: =R1410/S1410 -> 19.99 | AC1410: =R1410*T1410 -> 0 | AD1410: =R1410-(R1410*T1410) -> 39.98
A1411: 1410 | B1411: US-2016-122245 | C1411: 42638 | D1411: 42643 | E1411: Standard Class | F1411: AB-10105 | G1411: Adrian Barton | H1411: Consumer | I1411: United States | J1411: Phoenix | K1411: Arizona | L1411: 85023 | M1411: West | N1411: FUR-TA-10002356 | O1411: Furniture | P1411: Tables | Q1411: Bevis Boat-Shaped Conference Table | R1411: 393.165 | S1411: 3 | T1411: 0.5 | U1411: -204.4458 | V1411: =YEAR(C1411) -> 2016 | W1411: =TEXT(C1411,"mmm") -> Sep | X1411: =Sample___Superstore[[#This Row],[Order Year]]&"-"&Sample___Superstore[[#This Row],[Order Month]] -> 2016-Sep | Y1411: =Sample___Superstore6[[#This Row],[Profit]]/Sample___Superstore6[[#This Row],[Sales]] -> -0.52 | Z1411: =D1411-C1411 -> 5 | AA1411: =U1411/S1411 -> -68.1486 | AB1411: =R1411/S1411 -> 131.055 | AC1411: =R1411*T1411 -> 196.5825 | AD1411: =R1411-(R1411*T1411) -> 196.5825
A1412: 1411 | B1412: CA-2017-105144 | C1412: 43043 | D1412: 43050 | E1412: Standard Class | F1412: SZ-20035 | G1412: Sam Zeldin | H1412: Home Office | I1412: United States | J1412: Grand Prairie | K1412: Texas | L1412: 75051 | M1412: Central | N1412: OFF-LA-10003923 | O1412: Office Supplies | P1412: Labels | Q1412: Alphabetical Labels for Top Tab Filing | R1412: 23.68 | S1412: 2 | T1412: 0.2 | U1412: 8.88 | V1412: =YEAR(C1412) -> 2017 | W1412: =TEXT(C1412,"mmm") -> Nov | X1412: =Sample___Superstore[[#This Row],[Order Year]]&"-"&Sample___Superstore[[#This Row],[Order Month]] -> 2017-Nov | Y1412: =Sample___Superstore6[[#This Row],[Profit]]/Sample___Superstore6[[#This Row],[Sales]] -> 0.375 | Z1412: =D1412-C1412 -> 7 | AA1412: =U1412/S1412 -> 4.44 | AB1412: =R1412/S1412 -> 11.84 | AC1412: =R1412*T1412 -> 4.736 | AD1412: =R1412-(R1412*T1412) -> 18.944
A1413: 1412 | B1413: CA-2016-136329 | C1413: 42560 | D1413: 42564 | E1413: Standard Class | F1413: JD-15895 | G1413: Jonathan Doherty | H1413: Corporate | I1413: United States | J1413: New York City | K1413: New York | L1413: 10035 | M1413: East | N1413: FUR-CH-10002335 | O1413: Furniture | P1413: Chairs | Q1413: Hon GuestStacker Chair | R1413: 408.006 | S1413: 2 | T1413: 0.1 | U1413: 72.5344 | V1413: =YEAR(C1413) -> 2016 | W1413: =TEXT(C1413,"mmm") -> Jul | X1413: =Sample___Superstore[[#This Row],[Order Year]]&"-"&Sample___Superstore[[#This Row],[Order Month]] -> 2016-Jul | Y1413: =Sample___Superstore6[[#This Row],[Profit]]/Sample___Superstore6[[#This Row],[Sales]] -> 0.17777778 | Z1413: =D1413-C1413 -> 4 | AA1413: =U1413/S1413 -> 36.2672 | AB1413: =R1413/S1413 -> 204.003 | AC1413: =R1413*T1413 -> 40.8006 | AD1413: =R1413-(R1413*T1413) -> 367.2054
A1414: 1413 | B1414: CA-2016-136329 | C1414: 42560 | D1414: 42564 | E1414: Standard Class | F1414: JD-15895 | G1414: Jonathan Doherty | H1414: Corporate | I1414: United States | J1414: New York City | K1414: New York | L1414: 10035 | M1414: East | N1414: FUR-FU-10000723 | O1414: Furniture | P1414: Furnishings | Q1414: Deflect-o EconoMat Studded, No Bevel Mat for Low Pile Carpeting | R1414: 165.28 | S1414: 4 | T1414: 0 | U1414: 14.8752 | V1414: =YEAR(C1414) -> 2016 | W1414: =TEXT(C1414,"mmm") -> Jul | X1414: =Sample___Superstore[[#This Row],[Order Year]]&"-"&Sample___Superstore[[#This Row],[Order Month]] -> 2016-Jul | Y1414: =Sample___Superstore6[[#This Row],[Profit]]/Sample___Superstore6[[#This Row],[Sales]] -> 0.09 | Z1414: =D1414-C1414 -> 4 | AA1414: =U1414/S1414 -> 3.7188 | AB1414: =R1414/S1414 -> 41.32 | AC1414: =R1414*T1414 -> 0 | AD1414: =R1414-(R1414*T1414) -> 165.28
A1415: 1414 | B1415: CA-2014-146640 | C1415: 41820 | D1415: 41825 | E1415: Standard Class | F1415: HA-14905 | G1415: Helen Abelman | H1415: Consumer | I1415: United States | J1415: New York City | K1415: New York | L1415: 10024 | M1415: East | N1415: OFF-BI-10002867 | O1415: Office Supplies | P1415: Binders | Q1415: GBC Recycled Regency Composition Covers | R1415: 334.768 | S1415: 7 | T1415: 0.2 | U1415: 108.7996 | V1415: =YEAR(C1415) -> 2014 | W1415: =TEXT(C1415,"mmm") -> Jun | X1415: =Sample___Superstore[[#This Row],[Order Year]]&"-"&Sample___Superstore[[#This Row],[Order Month]] -> 2014-Jun | Y1415: =Sample___Superstore6[[#This Row],[Profit]]/Sample___Superstore6[[#This Row],[Sales]] -> 0.325 | Z1415: =D1415-C1415 -> 5 | AA1415: =U1415/S1415 -> 15.5428 | AB1415: =R1415/S1415 -> 47.824 | AC1415: =R1415*T1415 -> 66.9536 | AD1415: =R1415-(R1415*T1415) -> 267.8144
A1416: 1415 | B1416: CA-2017-115994 | C1416: 42763 | D1416: 42766 | E1416: Second Class | F1416: BT-11305 | G1416: Beth Thompson | H1416: Home Office | I1416: United States | J1416: Costa Mesa | K1416: California | L1416: 92627 | M1416: West | N1416: TEC-AC-10000580 | O1416: Technology | P1416: Accessories | Q1416: Logitech G13 Programmable Gameboard with LCD Display | R1416: 239.97 | S1416: 3 | T1416: 0 | U1416: 26.3967 | V1416: =YEAR(C1416) -> 2017 | W1416: =TEXT(C1416,"mmm") -> Jan | X1416: =Sample___Superstore[[#This Row],[Order Year]]&"-"&Sample___Superstore[[#This Row],[Order Month]] -> 2017-Jan | Y1416: =Sample___Superstore6[[#This Row],[Profit]]/Sample___Superstore6[[#This Row],[Sales]] -> 0.11 | Z1416: =D1416-C1416 -> 3 | AA1416: =U1416/S1416 -> 8.7989 | AB1416: =R1416/S1416 -> 79.99 | AC1416: =R1416*T1416 -> 0 | AD1416: =R1416-(R1416*T1416) -> 239.97
A1417: 1416 | B1417: CA-2017-115994 | C1417: 42763 | D1417: 42766 | E1417: Second Class | F1417: BT-11305 | G1417: Beth Thompson | H1417: Home Office | I1417: United States | J1417: Costa Mesa | K1417: California | L1417: 92627 | M1417: West | N1417: FUR-FU-10003976 | O1417: Furniture | P1417: Furnishings | Q1417: DAX Executive Solid Wood Document Frame, Desktop or Hang, Mahogany, 5 x 7 | R1417: 37.74 | S1417: 3 | T1417: 0 | U1417: 12.8316 | V1417: =YEAR(C1417) -> 2017 | W1417: =TEXT(C1417,"mmm") -> Jan | X1417: =Sample___Superstore[[#This Row],[Order Year]]&"-"&Sample___Superstore[[#This Row],[Order Month]] -> 2017-Jan | Y1417: =Sample___Superstore6[[#This Row],[Profit]]/Sample___Superstore6[[#This Row],[Sales]] -> 0.34 | Z1417: =D1417-C1417 -> 3 | AA1417: =U1417/S1417 -> 4.2772 | AB1417: =R1417/S1417 -> 12.58 | AC1417: =R1417*T1417 -> 0 | AD1417: =R1417-(R1417*T1417) -> 37.74
A1418: 1417 | B1418: CA-2015-126697 | C1418: 42268 | D1418: 42271 | E1418: First Class | F1418: SV-20815 | G1418: Stuart Van | H1418: Corporate | I1418: United States | J1418: Houston | K1418: Texas | L1418: 77041 | M1418: Central | N1418: TEC-PH-10002922 | O1418: Technology | P1418: Phones | Q1418: ShoreTel ShorePhone IP 230 VoIP phone | R1418: 946.344 | S1418: 7 | T1418: 0.2 | U1418: 118.293 | V1418: =YEAR(C1418) -> 2015 | W1418: =TEXT(C1418,"mmm") -> Sep | X1418: =Sample___Superstore[[#This Row],[Order Year]]&"-"&Sample___Superstore[[#This Row],[Order Month]] -> 2015-Sep | Y1418: =Sample___Superstore6[[#This Row],[Profit]]/Sample___Superstore6[[#This Row],[Sales]] -> 0.125 | Z1418: =D1418-C1418 -> 3 | AA1418: =U1418/S1418 -> 16.899 | AB1418: =R1418/S1418 -> 135.192 | AC1418: =R1418*T1418 -> 189.2688 | AD1418: =R1418-(R1418*T1418) -> 757.0752
A1419: 1418 | B1419: CA-2015-126697 | C1419: 42268 | D1419: 42271 | E1419: First Class | F1419: SV-20815 | G1419: Stuart Van | H1419: Corporate | I1419: United States | J1419: Houston | K1419: Texas | L1419: 77041 | M1419: Central | N1419: TEC-AC-10004353 | O1419: Technology | P1419: Accessories | Q1419: Hypercom P1300 Pinpad | R1419: 151.2 | S1419: 3 | T1419: 0.2 | U1419: 32.13 | V1419: =YEAR(C1419) -> 2015 | W1419: =TEXT(C1419,"mmm") -> Sep | X1419: =Sample___Superstore[[#This Row],[Order Year]]&"-"&Sample___Superstore[[#This Row],[Order Month]] -> 2015-Sep | Y1419: =Sample___Superstore6[[#This Row],[Profit]]/Sample___Superstore6[[#This Row],[Sales]] -> 0.2125 | Z1419: =D1419-C1419 -> 3 | AA1419: =U1419/S1419 -> 10.71 | AB1419: =R1419/S1419 -> 50.4 | AC1419: =R1419*T1419 -> 30.24 | AD1419: =R1419-(R1419*T1419) -> 120.96
A1420: 1419 | B1420: CA-2015-126697 | C1420: 42268 | D1420: 42271 | E1420: First Class | F1420: SV-20815 | G1420: Stuart Van | H1420: Corporate | I1420: United States | J1420: Houston | K1420: Texas | L1420: 77041 | M1420: Central | N1420: FUR-FU-10001706 | O1420: Furniture | P1420: Furnishings | Q1420: Longer-Life Soft White Bulbs | R1420: 4.928 | S1420: 4 | T1420: 0.6 | U1420: -1.4784 | V1420: =YEAR(C1420) -> 2015 | W1420: =TEXT(C1420,"mmm") -> Sep | X1420: =Sample___Superstore[[#This Row],[Order Year]]&"-"&Sample___Superstore[[#This Row],[Order Month]] -> 2015-Sep | Y1420: =Sample___Superstore6[[#This Row],[Profit]]/Sample___Superstore6[[#This Row],[Sales]] -> -0.3 | Z1420: =D1420-C1420 -> 3 | AA1420: =U1420/S1420 -> -0.3696 | AB1420: =R1420/S1420 -> 1.232 | AC1420: =R1420*T1420 -> 2.9568 | AD1420: =R1420-(R1420*T1420) -> 1.9712
... A1970: 1969 | B1970: CA-2017-165841 | C1970: 43090 | D1970: 43097 | E1970: Standard Class | F1970: DB-13210 | G1970: Dean Braden | H1970: Consumer | I1970: United States | J1970: Paterson | K1970: New Jersey | L1970: 7501 | M1970: East | N1970: OFF-PA-10001144 | O1970: Office Supplies | P1970: Paper | Q1970: Xerox 1913 | R1970: 166.44 | S1970: 3 | T1970: 0 | U1970: 79.8912 | V1970: =YEAR(C1970) -> 2017 | W1970: =TEXT(C1970,"mmm") -> Dec | X1970: =Sample___Superstore[[#This Row],[Order Year]]&"-"&Sample___Superstore[[#This Row],[Order Month]] -> 2017-Dec | Y1970: =Sample___Superstore6[[#This Row],[Profit]]/Sample___Superstore6[[#This Row],[Sales]] -> 0.48 | Z1970: =D1970-C1970 -> 7 | AA1970: =U1970/S1970 -> 26.6304 | AB1970: =R1970/S1970 -> 55.48 | AC1970: =R1970*T1970 -> 0 | AD1970: =R1970-(R1970*T1970) -> 166.44
A1971: 1970 | B1971: CA-2017-117485 | C1971: 43001 | D1971: 43007 | E1971: Standard Class | F1971: BD-11320 | G1971: Bill Donatelli | H1971: Consumer | I1971: United States | J1971: Tulsa | K1971: Oklahoma | L1971: 74133 | M1971: Central | N1971: TEC-AC-10004659 | O1971: Technology | P1971: Accessories | Q1971: Imation Secure+ Hardware Encrypted USB 2.0 Flash Drive | V1971: =YEAR(C1971) -> 2017 | W1971: =TEXT(C1971,"mmm") -> Sep | X1971: =Sample___Superstore[[#This Row],[Order Year]]&"-"&Sample___Superstore[[#This Row],[Order Month]] -> 2017-Sep | Y1971: =Sample___Superstore6[[#This Row],[Profit]]/Sample___Superstore6[[#This Row],[Sales]] -> #DIV/0! | Z1971: =D1971-C1971 -> 6 | AA1971: =U1971/S1971 -> #DIV/0! | AB1971: =R1971/S1971 -> #DIV/0! | AC1971: =R1971*T1971 -> 0 | AD1971: =R1971-(R1971*T1971) -> 0
A1972: 1971 | B1972: CA-2017-140242 | C1972: 42861 | D1972: 42866 | E1972: Standard Class | F1972: ML-17755 | G1972: Max Ludwig | H1972: Home Office | I1972: United States | J1972: Chicago | K1972: Illinois | L1972: 60623 | M1972: Central | N1972: OFF-AR-10004752 | O1972: Office Supplies | P1972: Art | Q1972: Blackstonian Pencils | R1972: 6.408 | S1972: 3 | T1972: 0.2 | U1972: 0.6408 | V1972: =YEAR(C1972) -> 2017 | W1972: =TEXT(C1972,"mmm") -> May | X1972: =Sample___Superstore[[#This Row],[Order Year]]&"-"&Sample___Superstore[[#This Row],[Order Month]] -> 2017-May | Y1972: =Sample___Superstore6[[#This Row],[Profit]]/Sample___Superstore6[[#This Row],[Sales]] -> 0.1 | Z1972: =D1972-C1972 -> 5 | AA1972: =U1972/S1972 -> 0.2136 | AB1972: =R1972/S1972 -> 2.136 | AC1972: =R1972*T1972 -> 1.2816 | AD1972: =R1972-(R1972*T1972) -> 5.1264
A1973: 1972 | B1973: CA-2017-140242 | C1973: 42861 | D1973: 42866 | E1973: Standard Class | F1973: ML-17755 | G1973: Max Ludwig | H1973: Home Office | I1973: United States | J1973: Chicago | K1973: Illinois | L1973: 60623 | M1973: Central | N1973: TEC-AC-10004659 | O1973: Technology | P1973: Accessories | Q1973: Imation Secure+ Hardware Encrypted USB 2.0 Flash Drive | V1973: =YEAR(C1973) -> 2017 | W1973: =TEXT(C1973,"mmm") -> May | X1973: =Sample___Superstore[[#This Row],[Order Year]]&"-"&Sample___Superstore[[#This Row],[Order Month]] -> 2017-May | Y1973: =Sample___Superstore6[[#This Row],[Profit]]/Sample___Superstore6[[#This Row],[Sales]] -> #DIV/0! | Z1973: =D1973-C1973 -> 5 | AA1973: =U1973/S1973 -> #DIV/0! | AB1973: =R1973/S1973 -> #DIV/0! | AC1973: =R1973*T1973 -> 0 | AD1973: =R1973-(R1973*T1973) -> 0
A1974: 1973 | B1974: CA-2014-148950 | C1974: 41987 | D1974: 41992 | E1974: Standard Class | F1974: JD-16015 | G1974: Joy Daniels | H1974: Consumer | I1974: United States | J1974: Chicago | K1974: Illinois | L1974: 60610 | M1974: Central | N1974: OFF-BI-10001249 | O1974: Office Supplies | P1974: Binders | Q1974: Avery Heavy-Duty EZD View Binder with Locking Rings | R1974: 5.104 | S1974: 4 | T1974: 0.8 | U1974: -8.6768 | V1974: =YEAR(C1974) -> 2014 | W1974: =TEXT(C1974,"mmm") -> Dec | X1974: =Sample___Superstore[[#This Row],[Order Year]]&"-"&Sample___Superstore[[#This Row],[Order Month]] -> 2014-Dec | Y1974: =Sample___Superstore6[[#This Row],[Profit]]/Sample___Superstore6[[#This Row],[Sales]] -> -1.7 | Z1974: =D1974-C1974 -> 5 | AA1974: =U1974/S1974 -> -2.1692 | AB1974: =R1974/S1974 -> 1.276 | AC1974: =R1974*T1974 -> 4.0832 | AD1974: =R1974-(R1974*T1974) -> 1.0208
A1975: 1974 | B1975: CA-2014-148950 | C1975: 41987 | D1975: 41992 | E1975: Standard Class | F1975: JD-16015 | G1975: Joy Daniels | H1975: Consumer | I1975: United States | J1975: Chicago | K1975: Illinois | L1975: 60610 | M1975: Central | N1975: OFF-FA-10003059 | O1975: Office Supplies | P1975: Fasteners | Q1975: Assorted Color Push Pins | R1975: 2.896 | S1975: 2 | T1975: 0.2 | U1975: 0.4706 | V1975: =YEAR(C1975) -> 2014 | W1975: =TEXT(C1975,"mmm") -> Dec | X1975: =Sample___Superstore[[#This Row],[Order Year]]&"-"&Sample___Superstore[[#This Row],[Order Month]] -> 2014-Dec | Y1975: =Sample___Superstore6[[#This Row],[Profit]]/Sample___Superstore6[[#This Row],[Sales]] -> 0.1625 | Z1975: =D1975-C1975 -> 5 | AA1975: =U1975/S1975 -> 0.2353 | AB1975: =R1975/S1975 -> 1.448 | AC1975: =R1975*T1975 -> 0.5792 | AD1975: =R1975-(R1975*T1975) -> 2.3168
A1976: 1975 | B1976: CA-2014-148950 | C1976: 41987 | D1976: 41992 | E1976: Standard Class | F1976: JD-16015 | G1976: Joy Daniels | H1976: Consumer | I1976: United States | J1976: Chicago | K1976: Illinois | L1976: 60610 | M1976: Central | N1976: TEC-AC-10002718 | O1976: Technology | P1976: Accessories | Q1976: Belkin Standard 104 key USB Keyboard | R1976: 35.016 | S1976: 3 | T1976: 0.2 | U1976: -2.1885 | V1976: =YEAR(C1976) -> 2014 | W1976: =TEXT(C1976,"mmm") -> Dec | X1976: =Sample___Superstore[[#This Row],[Order Year]]&"-"&Sample___Superstore[[#This Row],[Order Month]] -> 2014-Dec | Y1976: =Sample___Superstore6[[#This Row],[Profit]]/Sample___Superstore6[[#This Row],[Sales]] -> -0.0625 | Z1976: =D1976-C1976 -> 5 | AA1976: =U1976/S1976 -> -0.7295 | AB1976: =R1976/S1976 -> 11.672 | AC1976: =R1976*T1976 -> 7.0032 | AD1976: =R1976-(R1976*T1976) -> 28.0128
A1977: 1976 | B1977: CA-2014-110408 | C1977: 41930 | D1977: 41932 | E1977: Second Class | F1977: AS-10225 | G1977: Alan Schoenberger | H1977: Corporate | I1977: United States | J1977: Montgomery | K1977: Alabama | L1977: 36116 | M1977: South | N1977: OFF-ST-10001522 | O1977: Office Supplies | P1977: Storage | Q1977: Gould Plastics 18-Pocket Panel Bin, 34w x 5-1/4d x 20-1/2h | R1977: 275.97 | S1977: 3 | T1977: 0 | U1977: 11.0388 | V1977: =YEAR(C1977) -> 2014 | W1977: =TEXT(C1977,"mmm") -> Oct | X1977: =Sample___Superstore[[#This Row],[Order Year]]&"-"&Sample___Superstore[[#This Row],[Order Month]] -> 2014-Oct | Y1977: =Sample___Superstore6[[#This Row],[Profit]]/Sample___Superstore6[[#This Row],[Sales]] -> 0.04 | Z1977: =D1977-C1977 -> 2 | AA1977: =U1977/S1977 -> 3.6796 | AB1977: =R1977/S1977 -> 91.99 | AC1977: =R1977*T1977 -> 0 | AD1977: =R1977-(R1977*T1977) -> 275.97
A1978: 1977 | B1978: CA-2014-110408 | C1978: 41930 | D1978: 41932 | E1978: Second Class | F1978: AS-10225 | G1978: Alan Schoenberger | H1978: Corporate | I1978: United States | J1978: Montgomery | K1978: Alabama | L1978: 36116 | M1978: South | N1978: TEC-PH-10002352 | O1978: Technology | P1978: Phones | Q1978: Avaya IP Phone 1140E VoIP phone | R1978: 1394.95 | S1978: 5 | T1978: 0 | U1978: 362.687 | V1978: =YEAR(C1978) -> 2014 | W1978: =TEXT(C1978,"mmm") -> Oct | X1978: =Sample___Superstore[[#This Row],[Order Year]]&"-"&Sample___Superstore[[#This Row],[Order Month]] -> 2014-Oct | Y1978: =Sample___Superstore6[[#This Row],[Profit]]/Sample___Superstore6[[#This Row],[Sales]] -> 0.26 | Z1978: =D1978-C1978 -> 2 | AA1978: =U1978/S1978 -> 72.5374 | AB1978: =R1978/S1978 -> 278.99 | AC1978: =R1978*T1978 -> 0 | AD1978: =R1978-(R1978*T1978) -> 1394.95
A1979: 1978 | B1979: CA-2014-110408 | C1979: 41930 | D1979: 41932 | E1979: Second Class | F1979: AS-10225 | G1979: Alan Schoenberger | H1979: Corporate | I1979: United States | J1979: Montgomery | K1979: Alabama | L1979: 36116 | M1979: South | N1979: FUR-CH-10003774 | O1979: Furniture | P1979: Chairs | Q1979: Global Wood Trimmed Manager's Task Chair, Khaki | R1979: 545.88 | S1979: 6 | T1979: 0 | U1979: 70.9644 | V1979: =YEAR(C1979) -> 2014 | W1979: =TEXT(C1979,"mmm") -> Oct | X1979: =Sample___Superstore[[#This Row],[Order Year]]&"-"&Sample___Superstore[[#This Row],[Order Month]] -> 2014-Oct | Y1979: =Sample___Superstore6[[#This Row],[Profit]]/Sample___Superstore6[[#This Row],[Sales]] -> 0.13 | Z1979: =D1979-C1979 -> 2 | AA1979: =U1979/S1979 -> 11.8274 | AB1979: =R1979/S1979 -> 90.98 | AC1979: =R1979*T1979 -> 0 | AD1979: =R1979-(R1979*T1979) -> 545.88
A1980: 1979 | B1980: CA-2015-109939 | C1980: 42132 | D1980: 42136 | E1980: Standard Class | F1980: AA-10375 | G1980: Allen Armold | H1980: Consumer | I1980: United States | J1980: Salem | K1980: Oregon | L1980: 97301 | M1980: West | N1980: OFF-AR-10000127 | O1980: Office Supplies | P1980: Art | Q1980: Newell 321 | R1980: 5.248 | S1980: 2 | T1980: 0.2 | U1980: 0.5904 | V1980: =YEAR(C1980) -> 2015 | W1980: =TEXT(C1980,"mmm") -> May | X1980: =Sample___Superstore[[#This Row],[Order Year]]&"-"&Sample___Superstore[[#This Row],[Order Month]] -> 2015-May | Y1980: =Sample___Superstore6[[#This Row],[Profit]]/Sample___Superstore6[[#This Row],[Sales]] -> 0.1125 | Z1980: =D1980-C1980 -> 4 | AA1980: =U1980/S1980 -> 0.2952 | AB1980: =R1980/S1980 -> 2.624 | AC1980: =R1980*T1980 -> 1.0496 | AD1980: =R1980-(R1980*T1980) -> 4.1984
A1981: 1980 | B1981: CA-2016-112669 | C1981: 42474 | D1981: 42474 | E1981: Same Day | F1981: KT-16465 | G1981: Kean Takahito | H1981: Consumer | I1981: United States | J1981: Glendale | K1981: Arizona | L1981: 85301 | M1981: West | N1981: FUR-CH-10004086 | O1981: Furniture | P1981: Chairs | Q1981: Hon 4070 Series Pagoda Armless Upholstered Stacking Chairs | R1981: 933.536 | S1981: 4 | T1981: 0.2 | U1981: 105.0228 | V1981: =YEAR(C1981) -> 2016 | W1981: =TEXT(C1981,"mmm") -> Apr | X1981: =Sample___Superstore[[#This Row],[Order Year]]&"-"&Sample___Superstore[[#This Row],[Order Month]] -> 2016-Apr | Y1981: =Sample___Superstore6[[#This Row],[Profit]]/Sample___Superstore6[[#This Row],[Sales]] -> 0.1125 | Z1981: =D1981-C1981 -> 0 | AA1981: =U1981/S1981 -> 26.2557 | AB1981: =R1981/S1981 -> 233.384 | AC1981: =R1981*T1981 -> 186.7072 | AD1981: =R1981-(R1981*T1981) -> 746.8288
A1982: 1981 | B1982: CA-2016-112669 | C1982: 42474 | D1982: 42474 | E1982: Same Day | F1982: KT-16465 | G1982: Kean Takahito | H1982: Consumer | I1982: United States | J1982: Glendale | K1982: Arizona | L1982: 85301 | M1982: West | N1982: OFF-ST-10001228 | O1982: Office Supplies | P1982: Storage | Q1982: Fellowes Personal Hanging Folder Files, Navy | R1982: 42.976 | S1982: 4 | T1982: 0.2 | U1982: 4.2976 | V1982: =YEAR(C1982) -> 2016 | W1982: =TEXT(C1982,"mmm") -> Apr | X1982: =Sample___Superstore[[#This Row],[Order Year]]&"-"&Sample___Superstore[[#This Row],[Order Month]] -> 2016-Apr | Y1982: =Sample___Superstore6[[#This Row],[Profit]]/Sample___Superstore6[[#This Row],[Sales]] -> 0.1 | Z1982: =D1982-C1982 -> 0 | AA1982: =U1982/S1982 -> 1.0744 | AB1982: =R1982/S1982 -> 10.744 | AC1982: =R1982*T1982 -> 8.5952 | AD1982: =R1982-(R1982*T1982) -> 34.3808
A1983: 1982 | B1983: CA-2015-119592 | C1983: 42352 | D1983: 42354 | E1983: Second Class | F1983: MM-18280 | G1983: Muhammed MacIntyre | H1983: Corporate | I1983: United States | J1983: Columbus | K1983: Georgia | L1983: 31907 | M1983: South | N1983: OFF-BI-10004187 | O1983: Office Supplies | P1983: Binders | Q1983: 3-ring staple pack | R1983: 3.76 | S1983: 2 | T1983: 0 | U1983: 1.8048 | V1983: =YEAR(C1983) -> 2015 | W1983: =TEXT(C1983,"mmm") -> Dec | X1983: =Sample___Superstore[[#This Row],[Order Year]]&"-"&Sample___Superstore[[#This Row],[Order Month]] -> 2015-Dec | Y1983: =Sample___Superstore6[[#This Row],[Profit]]/Sample___Superstore6[[#This Row],[Sales]] -> 0.48 | Z1983: =D1983-C1983 -> 2 | AA1983: =U1983/S1983 -> 0.9024 | AB1983: =R1983/S1983 -> 1.88 | AC1983: =R1983*T1983 -> 0 | AD1983: =R1983-(R1983*T1983) -> 3.76
A1984: 1983 | B1984: CA-2014-122749 | C1984: 41976 | D1984: 41982 | E1984: Standard Class | F1984: NG-18430 | G1984: Nathan Gelder | H1984: Consumer | I1984: United States | J1984: Oklahoma City | K1984: Oklahoma | L1984: 73120 | M1984: Central | N1984: TEC-PH-10003811 | O1984: Technology | P1984: Phones | Q1984: Jabra Supreme Plus Driver Edition Headset | R1984: 479.96 | S1984: 4 | T1984: 0 | U1984: 134.3888 | V1984: =YEAR(C1984) -> 2014 | W1984: =TEXT(C1984,"mmm") -> Dec | X1984: =Sample___Superstore[[#This Row],[Order Year]]&"-"&Sample___Superstore[[#This Row],[Order Month]] -> 2014-Dec | Y1984: =Sample___Superstore6[[#This Row],[Profit]]/Sample___Superstore6[[#This Row],[Sales]] -> 0.28 | Z1984: =D1984-C1984 -> 6 | AA1984: =U1984/S1984 -> 33.5972 | AB1984: =R1984/S1984 -> 119.99 | AC1984: =R1984*T1984 -> 0 | AD1984: =R1984-(R1984*T1984) -> 479.96
A1985: 1984 | B1985: CA-2014-164721 | C1985: 41968 | D1985: 41970 | E1985: Second Class | F1985: LW-16825 | G1985: Laurel Workman | H1985: Corporate | I1985: United States | J1985: Brentwood | K1985: California | L1985: 94513 | M1985: West | N1985: OFF-AP-10000240 | O1985: Office Supplies | P1985: Appliances | Q1985: Belkin F9G930V10-GRY 9 Outlet Surge | R1985: 320.88 | S1985: 6 | T1985: 0 | U1985: 93.0552 | V1985: =YEAR(C1985) -> 2014 | W1985: =TEXT(C1985,"mmm") -> Nov | X1985: =Sample___Superstore[[#This Row],[Order Year]]&"-"&Sample___Superstore[[#This Row],[Order Month]] -> 2014-Nov | Y1985: =Sample___Superstore6[[#This Row],[Profit]]/Sample___Superstore6[[#This Row],[Sales]] -> 0.29 | Z1985: =D1985-C1985 -> 2 | AA1985: =U1985/S1985 -> 15.5092 | AB1985: =R1985/S1985 -> 53.48 | AC1985: =R1985*T1985 -> 0 | AD1985: =R1985-(R1985*T1985) -> 320.88
... A9995: 9994 | B9995: CA-2017-119914 | C9995: 42859 | D9995: 42864 | E9995: Second Class | F9995: CC-12220 | G9995: Chris Cortes | H9995: Consumer | I9995: United States | J9995: Westminster | K9995: California | L9995: 92683 | M9995: West | N9995: OFF-AP-10002684 | O9995: Office Supplies | P9995: Appliances | Q9995: Acco 7-Outlet Masterpiece Power Center, Wihtout Fax/Phone Line Protection | R9995: 243.16 | S9995: 2 | T9995: 0 | U9995: 72.948 | V9995: =YEAR(C9995) -> 2017 | W9995: =TEXT(C9995,"mmm") -> May | X9995: =Sample___Superstore[[#This Row],[Order Year]]&"-"&Sample___Superstore[[#This Row],[Order Month]] -> 2017-May | Y9995: =Sample___Superstore6[[#This Row],[Profit]]/Sample___Superstore6[[#This Row],[Sales]] -> 0.3 | Z9995: =D9995-C9995 -> 5 | AA9995: =U9995/S9995 -> 36.474 | AB9995: =R9995/S9995 -> 121.58 | AC9995: =R9995*T9995 -> 0 | AD9995: =R9995-(R9995*T9995) -> 243.16

Sheet Data Analysis
C2: DATA ANALYSIS PART: | G2: CALCULATED FIELDS:
C4: Number of rows | D4: =COUNTA('Sample - Superstore'!#REF!) -> 1 | G4: AOV | H4: =SUM('Sample - Superstore'!R2:R9995)/D9 -> 458.22997
C5: Number of columns | D5: =COUNTA('Sample - Superstore'!A1:U1) -> 21 | G5: Total sales | H5: =SUM('Sample - Superstore'!R2:R9995) -> 2295273.9
C6: Earliest Order Date | D6: =MIN('Sample - Superstore'!C2:C9995) -> 41642 | G6: Total Profit | H6: =SUM('Sample - Superstore'!U2:U9995) -> 285988.28
C7: Latest Order Date | D7: =MAX('Sample - Superstore'!C2:C9995) -> 43099 | G7: Average Discount | H7: =AVERAGE('Sample - Superstore'!T2:T9995) -> 0.15619644
C8: Number of customers | D8: =COUNTA(_xlfn.UNIQUE('Sample - Superstore'!F2:F9995)) -> 793
C9: Number of orders | D9: =COUNTA(_xlfn.UNIQUE('Sample - Superstore'!B2:B9995)) -> 5009
C10: Number of products | D10: =COUNTA(_xlfn.UNIQUE('Sample - Superstore'!N2:N9995)) -> 1862
C11: Number of categories | D11: =COUNTA(_xlfn.UNIQUE('Sample - Superstore'!O2:O9995)) -> 3
C12: Number of regions | D12: =COUNTA(_xlfn.UNIQUE('Sample - Superstore'!M2:M9995)) -> 4
